odoo9_addon_hr_phone-9.0.1.0.0.99.dev4-py2.7-nspkg.pth
odoo9_addon_hr_phone-9.0.1.0.0.99.dev4.dist-info/METADATA
odoo9_addon_hr_phone-9.0.1.0.0.99.dev4.dist-info/RECORD
odoo9_addon_hr_phone-9.0.1.0.0.99.dev4.dist-info/WHEEL
odoo9_addon_hr_phone-9.0.1.0.0.99.dev4.dist-info/namespace_packages.txt
odoo9_addon_hr_phone-9.0.1.0.0.99.dev4.dist-info/top_level.txt
odoo_addons/hr_phone/__init__.py
odoo_addons/hr_phone/__openerp__.py
odoo_addons/hr_phone/hr_phone.py
odoo_addons/hr_phone/hr_view.xml
odoo_addons/hr_phone/security/ir.model.access.csv
odoo_addons/hr_phone/static/description/icon.png
